{
  "project_info": {
    "project_number": "38877609195",
    "project_id": "a-guarantee-c420d",
    "storage_bucket": "a-guarantee-c420d.appspot.com"
  },
  "client": [
    {
      "client_info": {
        "mobilesdk_app_id": "1:38877609195:android:3d6348d7c533cb408e12ae",
        "android_client_info": {
          "package_name": "com.example.a_guarantee"
        }
      },
      "oauth_client": [],
      "api_key": [
        {
          "current_key": "AIzaSyDKi0oeGAnyKAjinLSF_Xo89fiHLRQX8g0"
        }
      ],
      "services": {
        "appinvite_service": {
          "other_platform_oauth_client": []
        }
      }
    }
  ],
  "configuration_version": "1"
}